cc/__init__.py
cc/admin.py
cc/audit.py
cc/forms.py
cc/models.py
cc/settings.py
cc/signals.py
cc/tasks.py
cc/urls.py
cc/validator.py
cc/views.py
cc/migrations/0001_initial.py
cc/migrations/0002_auto_20150105_1859.py
cc/migrations/0003_auto_20150106_1041.py
cc/migrations/0004_txid_not_uniq.py
cc/migrations/0005_currency_dust.py
cc/migrations/0006_auto_20160519_1952.py
cc/migrations/0007_withdrawtransaction_state.py
cc/migrations/0008_withdrawtransaction_state.py
cc/migrations/0009_WT_ixid_index.py
cc/migrations/0010_withdrawtransaction_walletconflicts.py
cc/migrations/0011_magicbyte_charfield.py
cc/migrations/__init__.py
cc/tests/__init__.py
cc/tests/tests_bitcoin_regtest.py
cc/tests/tests_dash_regtest.py
cc/tests/tests_litecoin_regtest.py
cc/tests/tests_mock.py
cc/tests/tests_zcash_regtest.py
django_cc-0.2.3.dist-info/LICENSE
django_cc-0.2.3.dist-info/METADATA
django_cc-0.2.3.dist-info/WHEEL
django_cc-0.2.3.dist-info/top_level.txt
django_cc-0.2.3.dist-info/RECORD
