Metadata-Version: 2.1
Name: django-cc
Version: 0.2.3
Summary: Django wallet for Bitcoin and other cryptocurrencies
Home-page: https://github.com/limpbrains/django-cc
Author: Ivan Vershigora
Author-email: ivan.vershigora@gmail.com
License: MIT License
Download-URL: https://github.com/limpbrains/django-cc/tarball/0.2.3
Keywords: bitcoin django wallet cryptocurrency litecoin zcash dogecoin dash
Platform: UNKNOWN
Classifier: Development Status :: 5 - Production/Stable
Classifier: Framework :: Django
Classifier: Intended Audience :: Developers
Classifier: License :: OSI Approved :: MIT License
Classifier: Programming Language :: Python :: 3
Classifier: Programming Language :: Python :: 3.4
Classifier: Programming Language :: Python :: 3.5
Classifier: Programming Language :: Python :: 3.6
Classifier: Topic :: Software Development :: Build Tools
Requires-Dist: celery (>=3)
Requires-Dist: Django (>=1.7)
Requires-Dist: mock
Requires-Dist: pycoin (>=0.90)
Requires-Dist: python-bitcoinrpc (>=1.0)
